image_to_scan/__init__.py
image_to_scan/app.py
image_to_scan/core.py
image_to_scan-0.0.6.dist-info/LICENSE
image_to_scan-0.0.6.dist-info/METADATA
image_to_scan-0.0.6.dist-info/WHEEL
image_to_scan-0.0.6.dist-info/entry_points.txt
image_to_scan-0.0.6.dist-info/top_level.txt
image_to_scan-0.0.6.dist-info/RECORD
