Metadata-Version: 2.1
Name: image-to-scan
Version: 0.0.6
Summary: Helps you transform a photo to a scanned document
Home-page: https://github.com/FrancescElies/image-to-scan
License: UNKNOWN
Platform: UNKNOWN
Classifier: Programming Language :: Python :: 3
Classifier: License :: OSI Approved :: Mozilla Public License 2.0 (MPL 2.0)
Requires-Python: >=3.0
Requires-Dist: opencv-python-headless (<5,>=4)
Requires-Dist: numpy (<2,>=1)
Requires-Dist: typer[all] (<1,>=0)
Requires-Dist: setuptools
